srunpy/__init__.py
srunpy/entry.py
srunpy/interface.py
srunpy/ip_utils.py
srunpy/srun.py
srunpy/html/MiSans-Medium.ttf
srunpy/html/__init__.py
srunpy/html/favicon.png
srunpy/html/index.html
srunpy/html/logo.svg
srunpy/html/script.js
srunpy/html/style.css
srunpy/html/icons/close-one.png
srunpy/html/icons/collapse.png
srunpy/html/icons/github.png
srunpy/html/icons/info.png
srunpy/html/icons/journey.ico
srunpy/html/icons/journey.png
srunpy/html/icons/journey_white.png
srunpy/html/icons/login.png
srunpy/html/icons/logo.ico
srunpy/html/icons/logo.png
srunpy/html/icons/logout.png
srunpy/html/icons/planet.png
srunpy/html/icons/refresh.png
srunpy/html/icons/setting.png
srunpy/html/icons/taskbar.png
srunpy/html/icons/user.png
srunpy-1.0.8.5.dist-info/licenses/LICENSE
srunpy-1.0.8.5.dist-info/METADATA
srunpy-1.0.8.5.dist-info/WHEEL
srunpy-1.0.8.5.dist-info/entry_points.txt
srunpy-1.0.8.5.dist-info/top_level.txt
srunpy-1.0.8.5.dist-info/RECORD
