Metadata-Version: 2.4
Name: srunpy
Version: 1.0.8.5
Summary: 适用于深澜网关的校园网第三方登录器
Home-page: https://github.com/HofNature/SRunPy-GUI
Author: HofNature
License: GPL-3.0
Keywords: srun,srunpy,srun-client,srun-gui,srunpy-gui,srun-client-gui,network,login,logout,gateway
Classifier: Development Status :: 4 - Beta
Classifier: Intended Audience :: Developers
Classifier: License :: OSI Approved :: GNU General Public License v3 (GPLv3)
Classifier: Programming Language :: Python :: 3
Classifier: Programming Language :: Python :: 3.7
Classifier: Programming Language :: Python :: 3.8
Classifier: Programming Language :: Python :: 3.9
Classifier: Programming Language :: Python :: 3.10
Classifier: Programming Language :: Python :: 3.11
Classifier: Programming Language :: Python :: 3.12
Classifier: Programming Language :: Python :: 3.13
Classifier: Operating System :: OS Independent
Requires-Python: >=3.7
License-File: LICENSE
Requires-Dist: requests
Requires-Dist: pystray; platform_system == "Windows"
Requires-Dist: pywebview; platform_system == "Windows"
Requires-Dist: pywin32; platform_system == "Windows"
Requires-Dist: win10toast; platform_system == "Windows"
Requires-Dist: pycryptodome; platform_system == "Windows"
Provides-Extra: qt
Requires-Dist: pywebview[qt]; extra == "qt"
Provides-Extra: build
Requires-Dist: pywebview; extra == "build"
Requires-Dist: nuitka; extra == "build"
Dynamic: author
Dynamic: classifier
Dynamic: description
Dynamic: description-content-type
Dynamic: home-page
Dynamic: keywords
Dynamic: license
Dynamic: license-file
Dynamic: provides-extra
Dynamic: requires-dist
Dynamic: requires-python
Dynamic: summary
